WeComMsg/WeComMsg.py
WeComMsg/__init__.py
wecommsg-1.0.9.dist-info/METADATA
wecommsg-1.0.9.dist-info/WHEEL
wecommsg-1.0.9.dist-info/top_level.txt
wecommsg-1.0.9.dist-info/RECORD
