Metadata-Version: 2.4
Name: WeComMsg
Version: 1.0.9
Summary: 发送企业微信消息的程序
Author: DongYang
Author-email: 649898871@qq.com
Requires-Dist: requests
